{
    "UxmlGuid": "2097220ea2db8436ea84ac4ec796e6aa",
    "UxmlPath": "Assets/MyPackages/M Studio/Editor/UI Builder/ItemEditor.uxml",
    "CanvasX": 0,
    "CanvasY": 0,
    "CanvasWidth": 675,
    "CanvasHeight": 680,
    "MatchGameView": false,
    "ZoomScale": 1.0,
    "PanOffset": {
        "x": 21.466644287109376,
        "y": 20.999969482421876
    },
    "ColorModeBackgroundOpacity": 1.0,
    "ImageModeCanvasBackgroundOpacity": 1.0,
    "CameraModeCanvasBackgroundOpacity": 1.0,
    "EnableCanvasBackground": false,
    "CanvasBackgroundMode": 0,
    "CanvasBackgroundColor": {
        "r": 0.0,
        "g": 0.0,
        "b": 0.0,
        "a": 255.0
    },
    "CanvasBackgroundImage": {
        "instanceID": 0
    },
    "CanvasBackgroundImageScaleMode": 1,
    "CanvasBackgroundCameraName": ""
}